cmr/__init__.py
connect/utils/terminal/markdown/__init__.py
connect/utils/terminal/markdown/components.py
connect/utils/terminal/markdown/emoji.py
connect/utils/terminal/markdown/node.py
connect/utils/terminal/markdown/renderer.py
connect/utils/terminal/markdown/theme.py
connect_markdown_renderer-3.0.0.dist-info/LICENSE
connect_markdown_renderer-3.0.0.dist-info/METADATA
connect_markdown_renderer-3.0.0.dist-info/WHEEL
connect_markdown_renderer-3.0.0.dist-info/RECORD
