Metadata-Version: 2.1
Name: connect-markdown-renderer
Version: 3.0.0
Summary: Connect Markdown Renderer
Home-page: https://connect.cloudblue.com
License: Apache-2.0
Author: CloudBlue
Requires-Python: >=3.8,<4
Classifier: License :: OSI Approved :: Apache Software License
Classifier: Programming Language :: Python :: 3
Classifier: Programming Language :: Python :: 3.8
Classifier: Programming Language :: Python :: 3.9
Classifier: Programming Language :: Python :: 3.10
Classifier: Programming Language :: Python :: 3.11
Requires-Dist: markdown-it-py (>=2.2.0,<3.0.0)
Requires-Dist: rich (>=12.4.4,<13)
Project-URL: Documentation, https://github.com/cloudblue/connect-markdown-renderer
Project-URL: Repository, https://github.com/cloudblue/connect-markdown-renderer
